<?xml version="1.0" encoding="UTF-8" standalone="no"?><artiklar><skapad-tid>2014-09-01 07:00</skapad-tid><info><meddelande>Läs användarvillkoren på www.systembolaget.se. Begreppet Modul används inte längre i Systembolagets verksamhet. Det innebär att det även har tagits bort från våra API-filer.</meddelande></info><artikel><nr>1191404</nr><Artikelid>776777</Artikelid><Varnummer>11914</Varnummer><Namn>BrewDog Mix</Namn><Namn2>Dead Pony Club, Libertine Black Ale, Jack Hammer, Cocoa Psycho</Namn2><Prisinklmoms>99.600</Prisinklmoms><Volymiml>1320</Volymiml><PrisPerLiter>75.45</PrisPerLiter><Saljstart>2013-12-02</Saljstart><Slutlev> </Slutlev><Varugrupp>Öl, Flera typer</Varugrupp><Forpackning>4 fl à 330 ml</Forpackning><Forslutning/><Ursprung/><Ursprunglandnamn>Storbritannien</Ursprunglandnamn><Producent>BrewDog</Producent><Leverantor>Cask Sweden AB</Leverantor><Argang/><Provadargang/><Alkoholhalt>7.1%</Alkoholhalt><Sortiment>FS</Sortiment><Ekologisk>0</Ekologisk><Koscher>0</Koscher><image>http://www.systembolaget.se/imagevaultfiles/id_25065/cf_1915/776777.jpg</image></artikel><artikel><nr>148904</nr><Artikelid>825642</Artikelid><Varnummer>1489</Varnummer><Namn>Hofbräu München</Namn><Namn2>Mixpack</Namn2><Prisinklmoms>71.600</Prisinklmoms><Volymiml>2000</Volymiml><PrisPerLiter>35.8</PrisPerLiter><Saljstart>2014-06-02</Saljstart><Slutlev> </Slutlev><Varugrupp>Öl, Flera typer</Varugrupp><Forpackning>4 fl à 500 ml</Forpackning><Forslutning/><Ursprung/><Ursprunglandnamn>Tyskland</Ursprunglandnamn><Producent>Staatliches Hofbräuhaus in München</Producent><Leverantor>Galatea Spirits AB</Leverantor><Argang/><Provadargang/><Alkoholhalt>5.2%</Alkoholhalt><Sortiment>FSN</Sortiment><Ekologisk>0</Ekologisk><Koscher>0</Koscher><image>http://www.systembolaget.se/imagevaultfiles/id_28317/cf_1915/825642.jpg</image></artikel><artikel><nr>161304</nr><Artikelid>758406</Artikelid><Varnummer>1613</Varnummer><Namn>Samuel Adams</Namn><Namn2>Fantastic Four</Namn2><Prisinklmoms>83.200</Prisinklmoms><Volymiml>1420</Volymiml><PrisPerLiter>58.59</PrisPerLiter><Saljstart>2013-09-02</Saljstart><Slutlev> </Slutlev><Varugrupp>Öl, Flera typer</Varugrupp><Forpackning>4 flaskor à 355 ml</Forpackning><Forslutning/><Ursprung/><Ursprunglandnamn>USA</Ursprunglandnamn><Producent>Samuel Adams</Producent><Leverantor>Galatea Spirits AB</Leverantor><Argang/><Provadargang/><Alkoholhalt>6.3%</Alkoholhalt><Sortiment>BS</Sortiment><Ekologisk>0</Ekologisk><Koscher>0</Koscher></artikel><artikel><nr>8070109</nr><Artikelid>865991</Artikelid><Varnummer>80701</Varnummer><Namn>Trippelale</Namn><Namn2>Älvdans Ipanema Rökstout</Namn2><Prisinklmoms>99.000</Prisinklmoms><Volymiml>1500</Volymiml><PrisPerLiter>66</PrisPerLiter><Saljstart>2014-07-01</Saljstart><Slutlev> </Slutlev><Varugrupp>Öl, Flera typer</Varugrupp><Forpackning>3 fl à 500 ml</Forpackning><Forslutning/><Ursprung>Skåne län, Kristianstads kommun</Ursprung><Ursprunglandnamn>Sverige</Ursprunglandnamn><Producent>Charlis Brygghus</Producent><Leverantor>Kasper Schönhult AB (Charlis Brygghus)</Leverantor><Argang/><Provadargang/><Alkoholhalt>5.4%</Alkoholhalt><Sortiment>TSLS</Sortiment><Ekologisk>0</Ekologisk><Koscher>0</Koscher><image>http://www.systembolaget.se/imagevaultfiles/id_28415/cf_1915/865991.jpg</image></artikel><artikel><nr>8844509</nr><Artikelid>811483</Artikelid><Varnummer>88445</Varnummer><Namn>Mission Brewery</Namn><Namn2>Beer Mix</Namn2><Prisinklmoms>936.000</Prisinklmoms><Volymiml>8520</Volymiml><PrisPerLiter>109.86</PrisPerLiter><Saljstart>2013-12-02</Saljstart><Slutlev> </Slutlev><Varugrupp>Öl, Flera typer</Varugrupp><Forpackning>24 fl à 355 ml</Forpackning><Forslutning/><Ursprung/><Ursprunglandnamn>USA</Ursprunglandnamn><Producent>Mission Brewery</Producent><Leverantor>CHill Creek AB</Leverantor><Argang/><Provadargang/><Alkoholhalt>8.2%</Alkoholhalt><Sortiment>BS</Sortiment><Ekologisk>0</Ekologisk><Koscher>0</Koscher></artikel><artikel><nr>8845809</nr><Artikelid>735459</Artikelid><Varnummer>88458</Varnummer><Namn>Störtebeker</Namn><Namn2>Provsmakarlåda</Namn2><Prisinklmoms>142.200</Prisinklmoms><Volymiml>3000</Volymiml><PrisPerLiter>47.4</PrisPerLiter><Saljstart>2013-04-01</Saljstart><Slutlev> </Slutlev><Varugrupp>Öl, Flera typer</Varugrupp><Forpackning>6 flaskor à 500 ml</Forpackning><Forslutning/><Ursprung/><Ursprunglandnamn>Tyskland</Ursprunglandnamn><Producent>Stralsunder Brauerei</Producent><Leverantor>Heba Food &amp; Beverages AB</Leverantor><Argang/><Provadargang/><Alkoholhalt>4.9%</Alkoholhalt><Sortiment>BS</Sortiment><Ekologisk>0</Ekologisk><Koscher>0</Koscher></artikel><artikel><nr>8863709</nr><Artikelid>804042</Artikelid><Varnummer>88637</Varnummer><Namn>Två Bryggare</Namn><Namn2>Tjeckiska Julkalender</Namn2><Prisinklmoms>500.000</Prisinklmoms><Volymiml>10000</Volymiml><PrisPerLiter>50</PrisPerLiter><Saljstart>2013-11-01</Saljstart><Slutlev> </Slutlev><Varugrupp>Öl, Flera typer</Varugrupp><Forpackning>20 fl à 500 ml</Forpackning><Forslutning/><Ursprung/><Ursprunglandnamn>Tjeckien</Ursprunglandnamn><Producent>Pivovary Lobkowicz</Producent><Leverantor>Österlenbryggarna AB</Leverantor><Argang/><Provadargang/><Alkoholhalt>4.6%</Alkoholhalt><Sortiment>BS</Sortiment><Ekologisk>0</Ekologisk><Koscher>0</Koscher></artikel><artikel><nr>8873109</nr><Artikelid>800329</Artikelid><Varnummer>88731</Varnummer><Namn>Byaregårdens</Namn><Namn2>Fägnad</Namn2><Prisinklmoms>84.700</Prisinklmoms><Volymiml>990</Volymiml><PrisPerLiter>85.56</PrisPerLiter><Saljstart>2013-11-01</Saljstart><Slutlev> </Slutlev><Varugrupp>Öl, Flera typer</Varugrupp><Forpackning>3 flaskor à 330 ml</Forpackning><Forslutning/><Ursprung>Hallands län, Varbergs kommun</Ursprung><Ursprunglandnamn>Sverige</Ursprunglandnamn><Producent>Byaregårdens Brygghus HB</Producent><Leverantor>Byaregårdens Brygghus HB</Leverantor><Argang/><Provadargang/><Alkoholhalt>5.5%</Alkoholhalt><Sortiment>TSLS</Sortiment><Ekologisk>0</Ekologisk><Koscher>0</Koscher></artikel><artikel><nr>8903909</nr><Artikelid>835840</Artikelid><Varnummer>89039</Varnummer><Namn>Midtfyns Provsmakningslåda</Namn><Namn2/><Prisinklmoms>570.900</Prisinklmoms><Volymiml>6000</Volymiml><PrisPerLiter>95.15</PrisPerLiter><Saljstart>2014-03-01</Saljstart><Slutlev> </Slutlev><Varugrupp>Öl, Flera typer</Varugrupp><Forpackning>12 fl à 500 ml</Forpackning><Forslutning/><Ursprung/><Ursprunglandnamn>Danmark</Ursprunglandnamn><Producent>Midtfyns Bryghus</Producent><Leverantor>Amka Vinimport AB</Leverantor><Argang/><Provadargang/><Alkoholhalt>8.3%</Alkoholhalt><Sortiment>BS</Sortiment><Ekologisk>0</Ekologisk><Koscher>0</Koscher></artikel><artikel><nr>8950509</nr><Artikelid>811800</Artikelid><Varnummer>89505</Varnummer><Namn>Monks Belgian Mix</Namn><Namn2>No 1</Namn2><Prisinklmoms>924.000</Prisinklmoms><Volymiml>7290</Volymiml><PrisPerLiter>126.75</PrisPerLiter><Saljstart>2013-12-02</Saljstart><Slutlev> </Slutlev><Varugrupp>Öl, Flera typer</Varugrupp><Forpackning>Flera flaskor</Forpackning><Forslutning/><Ursprung/><Ursprunglandnamn>Belgien</Ursprunglandnamn><Producent>Flera producenter</Producent><Leverantor>Panogruppen AB</Leverantor><Argang/><Provadargang/><Alkoholhalt>7.2%</Alkoholhalt><Sortiment>BS</Sortiment><Ekologisk>0</Ekologisk><Koscher>0</Koscher></artikel><artikel><nr>8982309</nr><Artikelid>735488</Artikelid><Varnummer>89823</Varnummer><Namn>De Graal</Namn><Namn2>Belgobox</Namn2><Prisinklmoms>601.500</Prisinklmoms><Volymiml>6210</Volymiml><PrisPerLiter>96.86</PrisPerLiter><Saljstart>2013-04-01</Saljstart><Slutlev> </Slutlev><Varugrupp>Öl, Flera typer</Varugrupp><Forpackning>Flera flaskor</Forpackning><Forslutning/><Ursprung/><Ursprunglandnamn>Belgien</Ursprunglandnamn><Producent>Brewery De Graal</Producent><Leverantor>Pilsnergubbarna AB</Leverantor><Argang/><Provadargang/><Alkoholhalt>6.6%</Alkoholhalt><Sortiment>BS</Sortiment><Ekologisk>0</Ekologisk><Koscher>0</Koscher></artikel><artikel><nr>9202801</nr><Artikelid>840280</Artikelid><Varnummer>92028</Varnummer><Namn>Uinta Tinder Rauchbier</Namn><Namn2/><Prisinklmoms>99.900</Prisinklmoms><Volymiml>750</Volymiml><PrisPerLiter>133.2</PrisPerLiter><Saljstart>2014-06-02</Saljstart><Slutlev> </Slutlev><Varugrupp>Öl, Flera typer</Varugrupp><Forpackning>Flaska</Forpackning><Forslutning/><Ursprung/><Ursprunglandnamn>USA</Ursprunglandnamn><Producent>Uinta Brewing Company</Producent><Leverantor>AB Wicked Wine Sweden</Leverantor><Argang/><Provadargang/><Alkoholhalt>6.5%</Alkoholhalt><Sortiment>TSE</Sortiment><Ekologisk>0</Ekologisk><Koscher>0</Koscher></artikel></artiklar>